{
  "project_info": {
    "project_number": "658690353088",
    "firebase_url": "https://gruppe3flamme.firebaseio.com",
    "project_id": "gruppe3flamme",
    "storage_bucket": "gruppe3flamme.appspot.com"
  },
  "client": [
    {
      "client_info": {
        "mobilesdk_app_id": "1:658690353088:android:1993052061880878",
        "android_client_info": {
          "package_name": "no.hiof.emilie.efinder"
        }
      },
      "oauth_client": [
        {
          "client_id": "658690353088-db0p18jjt1tkjk1epn6rkst077l5607m.apps.googleusercontent.com",
          "client_type": 1,
          "android_info": {
            "package_name": "no.hiof.emilie.efinder",
            "certificate_hash": "1deb606e1575145ea91d055b76011d163b065c18"
          }
        },
        {
          "client_id": "658690353088-vh5k05i15nhkeqck0evo1m0bed8snnsi.apps.googleusercontent.com",
          "client_type": 3
        }
      ],
      "api_key": [
        {
          "current_key": "AIzaSyAUWHZKX8fzhxIGhUHEJ1j57my5I2yKq4A"
        }
      ],
      "services": {
        "analytics_service": {
          "status": 1
        },
        "appinvite_service": {
          "status": 2,
          "other_platform_oauth_client": [
            {
              "client_id": "658690353088-vh5k05i15nhkeqck0evo1m0bed8snnsi.apps.googleusercontent.com",
              "client_type": 3
            }
          ]
        },
        "ads_service": {
          "status": 2
        }
      }
    }
  ],
  "configuration_version": "1"
}